{
  "webs": [
    {
      "nombre": "Justicia Canarias – Procesos Selectivos",
      "url": "https://www.gobiernodecanarias.org/justicia/RecursosHumanos/ProcesosSelectivos/",
      "estado": "ok",
      "ultima_comprobacion": "2026-04-19T17:55:55.467992",
      "ultimo_cambio": null
    },
    {
      "nombre": "Cabildo de La Palma – Empleo Público",
      "url": "https://sedeelectronica.cabildodelapalma.es/sta/CarpetaPublic/doEvent?APP_CODE=STA&PAGE_CODE=PTS2_EMPLEO",
      "estado": "ok",
      "ultima_comprobacion": "2026-04-19T17:55:55.467992",
      "ultimo_cambio": null
    },
    {
      "nombre": "SCS – Listas de Empleo y Supletorias",
      "url": "https://www3.gobiernodecanarias.org/sanidad/scs/contenidoGenerico.jsp?idDocument=b66c1847-b3d7-11eb-9269-832e239ed123&idCarpeta=61e907e3-d473-11e9-9a19-e5198e027117",
      "estado": "ok",
      "ultima_comprobacion": "2026-04-19T17:55:55.467992",
      "ultimo_cambio": "2026-04-16T19:50:29.835816"
    },
    {
      "nombre": "SEPE – Funcionarios Interinos",
      "url": "https://www.sepe.es/HomeSepe/que-es-el-sepe/convocatorias/funcionarios-interinos.html",
      "estado": "ok",
      "ultima_comprobacion": "2026-04-19T17:55:55.467992",
      "ultimo_cambio": null
    }
  ],
  "historial": [
    {
      "fecha": "2026-04-06T18:37:47.856666",
      "web": "SCS – Listas de Empleo y Supletorias",
      "url": "https://www3.gobiernodecanarias.org/sanidad/scs/contenidoGenerico.jsp?idDocument=b66c1847-b3d7-11eb-9269-832e239ed123&idCarpeta=61e907e3-d473-11e9-9a19-e5198e027117",
      "cambios": [
        "[06/04/2026].",
        "[06/04/2026].",
        "[06/04/2026]."
      ]
    },
    {
      "fecha": "2026-04-07T19:43:01.767463",
      "web": "SCS – Listas de Empleo y Supletorias",
      "url": "https://www3.gobiernodecanarias.org/sanidad/scs/contenidoGenerico.jsp?idDocument=b66c1847-b3d7-11eb-9269-832e239ed123&idCarpeta=61e907e3-d473-11e9-9a19-e5198e027117",
      "cambios": [
        "[07/04/2026].",
        "[07/04/2026].",
        "[07/04/2026].",
        "[07/04/2026]."
      ]
    },
    {
      "fecha": "2026-04-08T19:49:47.654161",
      "web": "SCS – Listas de Empleo y Supletorias",
      "url": "https://www3.gobiernodecanarias.org/sanidad/scs/contenidoGenerico.jsp?idDocument=b66c1847-b3d7-11eb-9269-832e239ed123&idCarpeta=61e907e3-d473-11e9-9a19-e5198e027117",
      "cambios": [
        "[08/04/2026].",
        "[08/04/2026]."
      ]
    },
    {
      "fecha": "2026-04-09T19:54:36.766492",
      "web": "SCS – Listas de Empleo y Supletorias",
      "url": "https://www3.gobiernodecanarias.org/sanidad/scs/contenidoGenerico.jsp?idDocument=b66c1847-b3d7-11eb-9269-832e239ed123&idCarpeta=61e907e3-d473-11e9-9a19-e5198e027117",
      "cambios": [
        "[09/04/2026].",
        "[09/04/2026].",
        "[09/04/2026]."
      ]
    },
    {
      "fecha": "2026-04-13T19:57:59.812688",
      "web": "SCS – Listas de Empleo y Supletorias",
      "url": "https://www3.gobiernodecanarias.org/sanidad/scs/contenidoGenerico.jsp?idDocument=b66c1847-b3d7-11eb-9269-832e239ed123&idCarpeta=61e907e3-d473-11e9-9a19-e5198e027117",
      "cambios": [
        "[13/04/2026].",
        "[13/04/2026].",
        "[13/04/2026].",
        "[13/04/2026]."
      ]
    },
    {
      "fecha": "2026-04-14T19:56:28.735224",
      "web": "SCS – Listas de Empleo y Supletorias",
      "url": "https://www3.gobiernodecanarias.org/sanidad/scs/contenidoGenerico.jsp?idDocument=b66c1847-b3d7-11eb-9269-832e239ed123&idCarpeta=61e907e3-d473-11e9-9a19-e5198e027117",
      "cambios": [
        "[14/04/2026]."
      ]
    },
    {
      "fecha": "2026-04-15T19:55:42.169711",
      "web": "SCS – Listas de Empleo y Supletorias",
      "url": "https://www3.gobiernodecanarias.org/sanidad/scs/contenidoGenerico.jsp?idDocument=b66c1847-b3d7-11eb-9269-832e239ed123&idCarpeta=61e907e3-d473-11e9-9a19-e5198e027117",
      "cambios": [
        "[15/04/2026]."
      ]
    },
    {
      "fecha": "2026-04-16T19:50:29.835816",
      "web": "SCS – Listas de Empleo y Supletorias",
      "url": "https://www3.gobiernodecanarias.org/sanidad/scs/contenidoGenerico.jsp?idDocument=b66c1847-b3d7-11eb-9269-832e239ed123&idCarpeta=61e907e3-d473-11e9-9a19-e5198e027117",
      "cambios": [
        "[16/04/2026].",
        "[16/04/2026].",
        "[16/04/2026]."
      ]
    }
  ],
  "ultima_comprobacion": "2026-04-19T17:55:55.467992"
}